odoo/addons/l10n_fi_business_code_validate/README.rst
odoo/addons/l10n_fi_business_code_validate/__init__.py
odoo/addons/l10n_fi_business_code_validate/__manifest__.py
odoo/addons/l10n_fi_business_code_validate/data/res_partner_id_category.xml
odoo/addons/l10n_fi_business_code_validate/i18n/fi.po
odoo/addons/l10n_fi_business_code_validate/i18n/l10n_fi_business_code_validate.pot
odoo/addons/l10n_fi_business_code_validate/models/__init__.py
odoo/addons/l10n_fi_business_code_validate/models/res_partner_id_category.py
odoo/addons/l10n_fi_business_code_validate/static/description/icon.png
odoo/addons/l10n_fi_business_code_validate/tests/__init__.py
odoo/addons/l10n_fi_business_code_validate/tests/test_business_id_validate.py
odoo12_addon_l10n_fi_business_code_validate-12.0.1.0.0.99.dev2.dist-info/METADATA
odoo12_addon_l10n_fi_business_code_validate-12.0.1.0.0.99.dev2.dist-info/RECORD
odoo12_addon_l10n_fi_business_code_validate-12.0.1.0.0.99.dev2.dist-info/WHEEL
odoo12_addon_l10n_fi_business_code_validate-12.0.1.0.0.99.dev2.dist-info/top_level.txt
