Metadata-Version: 2.1
Name: odoo12-addon-l10n-fi-business-code-validate
Version: 12.0.1.0.0.99.dev2
Summary: Adds validation for partner_business_code
Home-page: https://odoo-community.org/
Author: Oy Tawasta Technologies Ltd., Odoo Community Association (OCA)
Author-email: support@odoo-community.org
License: AGPL-3
Platform: UNKNOWN
Classifier: Programming Language :: Python
Classifier: Framework :: Odoo
Classifier: License :: OSI Approved :: GNU Affero General Public License v3
Requires-Python: >=3.5
Requires-Dist: odoo12-addon-l10n-fi-business-code
Requires-Dist: odoo (<12.1dev,>=12.0a)
